mt_SetFile/MaxTrack.py
mt_SetFile/__init__.py
mt_SetFile/exampleKeypad.py
mt_SetFile/glob_search-dir.py
mt_SetFile/matchingLines.py
mt_SetFile/mt_SetFile.py
mt_SetFile/mt_SetFile_2021-03-29.py
mt_SetFile/myTextEdit.py
mt_SetFile-0.0.5.dist-info/LICENSE
mt_SetFile-0.0.5.dist-info/METADATA
mt_SetFile-0.0.5.dist-info/WHEEL
mt_SetFile-0.0.5.dist-info/top_level.txt
mt_SetFile-0.0.5.dist-info/RECORD
